relsad/StatDist/StatDist.py
relsad/StatDist/__init__.py
relsad/Table.py
relsad/Time.py
relsad/__init__.py
relsad/energy/__init__.py
relsad/energy/shedding.py
relsad/examples/CINELDI/CINELDI.png
relsad/examples/CINELDI/CINELDI_ICT_failed_ict_lines.pdf
relsad/examples/CINELDI/__init__.py
relsad/examples/CINELDI/load_and_prod.py
relsad/examples/CINELDI/network.py
relsad/examples/CINELDI/simulation.py
relsad/examples/IEEE16_modified/__init__.py
relsad/examples/IEEE16_modified/load_and_prod.py
relsad/examples/IEEE16_modified/network.py
relsad/examples/IEEE16_modified/simulation.py
relsad/examples/IEEE33/__init__.py
relsad/examples/IEEE33/load_and_prod.py
relsad/examples/IEEE33/network.py
relsad/examples/IEEE33/simulation.py
relsad/examples/IEEE69/__init__.py
relsad/examples/IEEE69/network.py
relsad/examples/RBTS2/__init__.py
relsad/examples/RBTS2/load_and_prod.py
relsad/examples/RBTS2/network.py
relsad/examples/RBTS2/simulation.py
relsad/examples/RBTS6/__init__.py
relsad/examples/RBTS6/network.py
relsad/examples/TEST10/__init__.py
relsad/examples/TEST10/load_and_prod.py
relsad/examples/TEST10/network.py
relsad/examples/TEST10/simulation.py
relsad/examples/load/__init__.py
relsad/examples/load/data/load_profiles_fasit.csv
relsad/examples/load/data/load_profiles_fasit.xlsx
relsad/examples/load/data/weather_data_rygge.csv
relsad/examples/load/load_and_gen_data.py
relsad/examples/tutorial/active_generation_units.py
relsad/examples/tutorial/grid_connected_microgrids.py
relsad/examples/tutorial/islanded_networks.py
relsad/examples/tutorial/monte_carlo.py
relsad/examples/tutorial/power_system_with_fallible_ict.py
relsad/examples/tutorial/power_system_with_ideal_ict.py
relsad/examples/tutorial/sequential.py
relsad/examples/tutorial/system.py
relsad/examples/tutorial/system_components.py
relsad/load/__init__.py
relsad/load/bus.py
relsad/loadflow/ac/__init__.py
relsad/loadflow/ac/bfs.py
relsad/network/__init__.py
relsad/network/components/Battery.py
relsad-0.2.15.dist-info/LICENSE
relsad-0.2.15.dist-info/WHEEL
relsad-0.2.15.dist-info/METADATA
relsad-0.2.15.dist-info/RECORD
