Metadata-Version: 2.1
Name: relsad
Version: 0.2.15
Summary: A package that facilitates reliability investigations of power systems
Home-page: https://github.com/stinefm/relsad
License: MIT
Author: Stine Fleischer Myhre
Requires-Python: >=3.8,<3.11
Classifier: License :: OSI Approved :: MIT License
Classifier: Programming Language :: Python :: 3
Classifier: Programming Language :: Python :: 3.8
Classifier: Programming Language :: Python :: 3.9
Classifier: Programming Language :: Python :: 3.10
Requires-Dist: matplotlib (>=3.5.1,<4.0.0)
Requires-Dist: pandas (>=1.4.1,<2.0.0)
Requires-Dist: scipy (>=1.8.0,<2.0.0)
Project-URL: Documentation, https://relsad.readthedocs.io/
Project-URL: Repository, https://github.com/stinefm/relsad
